kong/__init__.py
kong/acls.py
kong/auths.py
kong/certificates.py
kong/cli.py
kong/client.py
kong/components.py
kong/consumers.py
kong/plugins.py
kong/py.typed
kong/routes.py
kong/services.py
kong/snis.py
kong/utils.py
aio_kong-3.7.2.dist-info/LICENSE
aio_kong-3.7.2.dist-info/METADATA
aio_kong-3.7.2.dist-info/WHEEL
aio_kong-3.7.2.dist-info/entry_points.txt
aio_kong-3.7.2.dist-info/RECORD
