Metadata-Version: 2.3
Name: aio-kong
Version: 3.7.2
Summary: Asynchronous Kong Client
License: BSD-3-Clause
Author: Luca Sbardella
Author-email: luca@quantmind.com
Requires-Python: >=3.10,<4.0
Classifier: License :: OSI Approved :: BSD License
Classifier: Programming Language :: Python :: 3
Classifier: Programming Language :: Python :: 3.10
Classifier: Programming Language :: Python :: 3.11
Classifier: Programming Language :: Python :: 3.12
Classifier: Programming Language :: Python :: 3.13
Provides-Extra: cli
Requires-Dist: PyYAML (>=6.0) ; extra == "cli"
Requires-Dist: aiohttp (>=3.9.5)
Requires-Dist: click (>=8.1.3) ; extra == "cli"
Requires-Dist: rich (>=13.7.1) ; extra == "cli"
Project-URL: Issues, https://github.com/quantmind/aio-kong/issues
Project-URL: Repository, https://github.com/quantmind/aio-kong
